dj_environ-0.0.1.dist-info/DESCRIPTION.rst
dj_environ-0.0.1.dist-info/METADATA
dj_environ-0.0.1.dist-info/RECORD
dj_environ-0.0.1.dist-info/WHEEL
dj_environ-0.0.1.dist-info/metadata.json
dj_environ-0.0.1.dist-info/top_level.txt
environ/__init__.py
environ/environ.py
environ/test.py
environ/test_env.txt
