Metadata-Version: 2.0
Name: dj-environ
Version: 0.0.1
Summary: Dj-environ allows you to utilize 12factor inspired environment variables to configure your Django application.
Home-page: https://github.com/ratson/dj-environ
Author: Ratson
Author-email: contact@ratson.name
License: MIT License
Keywords: django environment variables 12factor
Platform: any
Classifier: Development Status :: 3 - Alpha
Classifier: Intended Audience :: Information Technology
Classifier: Programming Language :: Python
Classifier: Programming Language :: Python :: 2
Classifier: Programming Language :: Python :: 3
Classifier: Programming Language :: Python :: Implementation :: CPython
Classifier: Programming Language :: Python :: Implementation :: PyPy
Classifier: Topic :: Software Development :: Libraries :: Python Modules
Classifier: Topic :: Utilities
Classifier: License :: OSI Approved :: MIT License
Classifier: Framework :: Django
Requires-Dist: django
Requires-Dist: six
